{"alignment_evidence":{"key_lemmas":["Nat.add_assoc"],"span_mappings":[{"formal_identifiers":["Nat.add_assoc"],"nl_span":"Addition is associative"}]},"created_utc":"2026-06-19T06:00:00Z","formal_statement":"theorem ex06_add_assoc (a b c : Nat) : (a + b) + c = a + (b + c)","invariant_diff":{"demo_example":"ex06_add_assoc"},"natural_language_claim":"Addition is associative.","objections":[],"pair_id":"DEMO_EX06_ADD_ASSOC_PAIR","schema_id":"QA_HUMAN_FORMAL_PAIR_CERT.v1","status":"PROVED","trace_ref":{"replay_status":"SUCCESS","result_status":"SUCCESS","trace_id":"f928bd31f883bac84660982daecf5ed2c93b6c9977c5d88dad07eee2540cdb04"}}
