{
  "patients": [
    {
      "patient": "chb08",
      "dr2_f0": -0.0018,
      "p_f0": 1.0,
      "dr2_f2": 0.00813,
      "p_f2": 0.952692,
      "dr2_comb": 0.00701,
      "p_comb": 0.999538
    },
    {
      "patient": "chb09",
      "dr2_f0": 0.01563,
      "p_f0": 0.951018,
      "dr2_f2": 0.02701,
      "p_f2": 0.896615,
      "dr2_comb": 0.03964,
      "p_comb": 0.989778
    },
    {
      "patient": "chb10",
      "dr2_f0": 0.00968,
      "p_f0": 0.9533,
      "dr2_f2": 0.01621,
      "p_f2": 0.905231,
      "dr2_comb": 0.02592,
      "p_comb": 0.989211
    },
    {
      "patient": "chb12",
      "dr2_f0": -0.00082,
      "p_f0": 1.0,
      "dr2_f2": 0.06267,
      "p_f2": 0.140293,
      "dr2_comb": 0.0475,
      "p_comb": 0.656702
    },
    {
      "patient": "chb13",
      "dr2_f0": 0.09745,
      "p_f0": 0.255799,
      "dr2_f2": 0.00862,
      "p_f2": 0.948701,
      "dr2_comb": 0.10289,
      "p_comb": 0.638961
    },
    {
      "patient": "chb14",
      "dr2_f0": 0.01254,
      "p_f0": 0.984487,
      "dr2_f2": 0.10274,
      "p_f2": 0.736161,
      "dr2_comb": 0.1115,
      "p_comb": 0.967137
    }
  ],
  "aggregate": {
    "f0": {
      "mean_dr2": 0.02211,
      "n_pos": 4,
      "fisher_p": 0.99585954
    },
    "f2": {
      "mean_dr2": 0.03756,
      "n_pos": 6,
      "fisher_p": 0.95240941
    },
    "comb": {
      "mean_dr2": 0.05574,
      "n_pos": 6,
      "fisher_p": 0.99960705
    }
  }
}