{"alignment_evidence":{"key_lemmas":["Nat.zero_add"],"span_mappings":[{"formal_identifiers":["Nat.zero_add"],"nl_span":"Zero is a left identity for addition"}]},"created_utc":"2026-06-19T09:00:00Z","formal_statement":"theorem ex09_zero_add (n : Nat) : 0 + n = n","invariant_diff":{"demo_example":"ex09_zero_add"},"natural_language_claim":"Zero is a left identity for addition.","objections":[],"pair_id":"DEMO_EX09_ZERO_ADD_PAIR","schema_id":"QA_HUMAN_FORMAL_PAIR_CERT.v1","status":"PROVED","trace_ref":{"replay_status":"SUCCESS","result_status":"SUCCESS","trace_id":"25d66fc78d348b7907745ba43e0f8709b1aa1d2376729c9ce1ab25d84ee94e46"}}
